Workbook

Sheet Sales Dashboard
B2: SALES PERFORMANCE DASHBOARD
B3: Retail Sales Overview | Currency: EGP | Source: Analysis Ready
B5: TOTAL NET SALES | E5: TOTAL GROSS SALES | H5: TOTAL ORDERS | K5: AVG. ORDER VALUE
B6: ='Analysis Sales'!B5 | E6: ='Analysis Sales'!B4 | H6: ='Analysis Sales'!B7 | K6: ='Analysis Sales'!B8
B9: DISCOUNT AMOUNT | E9: QUANTITY SOLD
B10: ='Analysis Sales'!B6 | E10: ='Analysis Sales'!B9
H28: TOP 10 PRODUCTS BY NET SALES
H29: Product | I29: Net Sales (EGP) | J29: Qty Sold
H30: Perfume | I30: 40375 | J30: 45
H31: Skin Care Set | I31: 35255 | J31: 35
H32: Electric Kettle | I32: 31590 | J32: 37
H33: Headphones | I33: 29675.5 | J33: 50
H34: Blender | I34: 25860 | J34: 23
H35: Backpack | I35: 21780 | J35: 41
H36: Wireless Mouse | I36: 18228 | J36: 47
H37: Hair Dryer | I37: 17297.5 | J37: 21
H38: Trimmer | I38: 12915 | J38: 20
H39: LED Lamp | I39: 11147.5 | J39: 37
B43: Data quality note: 3 rows excluded from analysis due to missing/invalid required fields. Review Data Quality Summary.

Sheet Clean_Data
